pytope/__init__.py
pytope/demo.py
pytope/polytope.py
pytope-0.0.4.dist-info/METADATA
pytope-0.0.4.dist-info/RECORD
pytope-0.0.4.dist-info/WHEEL
pytope-0.0.4.dist-info/top_level.txt
