Metadata-Version: 2.1
Name: pytope
Version: 0.0.4
Summary: Polytope operations --- limited functionality
Home-page: https://github.com/heirung/pytope
Author: Tor Aksel N. Heirung
Author-email: github@torheirung.com
License: MIT
Platform: UNKNOWN
Requires-Python: >=3.6
